ory_hydra_client/__init__.py
ory_hydra_client/api_client.py
ory_hydra_client/api_response.py
ory_hydra_client/configuration.py
ory_hydra_client/exceptions.py
ory_hydra_client/py.typed
ory_hydra_client/rest.py
ory_hydra_client/api/__init__.py
ory_hydra_client/api/jwk_api.py
ory_hydra_client/api/metadata_api.py
ory_hydra_client/api/o_auth2_api.py
ory_hydra_client/api/oidc_api.py
ory_hydra_client/api/wellknown_api.py
ory_hydra_client/models/__init__.py
ory_hydra_client/models/accept_device_user_code_request.py
ory_hydra_client/models/accept_o_auth2_consent_request.py
ory_hydra_client/models/accept_o_auth2_consent_request_session.py
ory_hydra_client/models/accept_o_auth2_login_request.py
ory_hydra_client/models/create_json_web_key_set.py
ory_hydra_client/models/create_verifiable_credential_request_body.py
ory_hydra_client/models/credential_supported_draft00.py
ory_hydra_client/models/device_authorization.py
ory_hydra_client/models/device_user_auth_request.py
ory_hydra_client/models/error_o_auth2.py
ory_hydra_client/models/generic_error.py
ory_hydra_client/models/get_version200_response.py
ory_hydra_client/models/health_not_ready_status.py
ory_hydra_client/models/health_status.py
ory_hydra_client/models/introspected_o_auth2_token.py
ory_hydra_client/models/is_ready200_response.py
ory_hydra_client/models/is_ready503_response.py
ory_hydra_client/models/json_patch.py
ory_hydra_client/models/json_web_key.py
ory_hydra_client/models/json_web_key_set.py
ory_hydra_client/models/keyset_pagination_request_parameters.py
ory_hydra_client/models/keyset_pagination_response_headers.py
ory_hydra_client/models/o_auth2_client.py
ory_hydra_client/models/o_auth2_client_token_lifespans.py
ory_hydra_client/models/o_auth2_consent_request.py
ory_hydra_client/models/o_auth2_consent_request_open_id_connect_context.py
ory_hydra_client/models/o_auth2_consent_session.py
ory_hydra_client/models/o_auth2_login_request.py
ory_hydra_client/models/o_auth2_logout_request.py
ory_hydra_client-25.4.0.dist-info/LICENSE
ory_hydra_client-25.4.0.dist-info/METADATA
ory_hydra_client-25.4.0.dist-info/WHEEL
ory_hydra_client-25.4.0.dist-info/top_level.txt
ory_hydra_client-25.4.0.dist-info/RECORD
